README.md
setup.py
make_arq.egg-info/PKG-INFO
make_arq.egg-info/SOURCES.txt
make_arq.egg-info/dependency_links.txt
make_arq.egg-info/entry_points.txt
make_arq.egg-info/requires.txt
make_arq.egg-info/top_level.txt
src/make_arq/__init__.py
src/make_arq/_makearq.c
src/make_arq/make_arq.py